{
  "form": {
    "/data/lakehouse": {
      "templatePath": "/data/lakehouse/index.html",
      "isModal": true,
      "modalId": "data-lakehouse-modal",
      "formData": {
        "title": "Talk to our Apache Spark solution architects",
        "formId": "6203",
        "returnUrl": "/data/lakehouse#contact-form-success",
        "product": ""
      },
      "fieldsets": [
        {
          "title": "Tell us more about your Spark use case",
          "id": "comments",
          "isRequired": false,
          "fields": [
            {
              "type": "long-text",
              "id": "comments",
              "placeholder": "Anything you'd like to communicate about your needs or interests?"
            }
          ]
        },
        {
          "title": "How should we get in touch?",
          "id": "about-you",
          "noCommentsFromLead": true,
          "fields": [
            {
              "type": "tel",
              "id": "phone",
              "label": "Mobile/cell phone number"
            }
          ]
        }
      ]
    }
  }
}
